flippy/__init__.py
flippy/__main__.py
flippy/lapse.py
flippy-0.1.1.dist-info/METADATA
flippy-0.1.1.dist-info/RECORD
flippy-0.1.1.dist-info/WHEEL
flippy-0.1.1.dist-info/entry_points.txt
flippy-0.1.1.dist-info/top_level.txt
