Metadata-Version: 2.1
Name: flippy
Version: 0.1.1
Summary: Build videos from image directories
Home-page: https://github.com/ecrows/flippy
Author: ecrows
License: MIT
Keywords: opencv video flipbook overlay python3 timelapse lapse flip flipy
Platform: UNKNOWN
Classifier: Development Status :: 4 - Beta
Classifier: License :: OSI Approved :: MIT License
Classifier: Programming Language :: Python :: 3
Classifier: Topic :: Multimedia :: Video
Requires-Dist: numpy
Requires-Dist: opencv-python
